Metadata-Version: 2.4
Name: github-shell
Version: 1.2.0
Summary: A GitHub simulation shell with automatic update feature
Home-page: https://github.com/wjr-2015/github-shell
Author: wjr-2015
Author-email: wjr-2015 <wangjinrui_150328@126.com>
Project-URL: Homepage, https://github.com/wjr-2015/github-shell
Project-URL: Repository, https://github.com/wjr-2015/github-shell
Classifier: Programming Language :: Python :: 3
Classifier: License :: OSI Approved :: MIT License
Classifier: Operating System :: OS Independent
Requires-Python: >=3.6
License-File: LICENSE
Requires-Dist: requests>=2.25.0
Requires-Dist: cryptography>=38.0.0
Dynamic: author
Dynamic: home-page
Dynamic: license-file
Dynamic: requires-python
